README
setup.py
memoize/__init__.py
memoize/memoize.py
simple_gae_memoize.egg-info/PKG-INFO
simple_gae_memoize.egg-info/SOURCES.txt
simple_gae_memoize.egg-info/dependency_links.txt
simple_gae_memoize.egg-info/top_level.txt