Metadata-Version: 1.0
Name: simple-gae-memoize
Version: 0.0.2
Summary: A decorator to memoize App Engine functions using the memcache
Home-page: http://packages.python.org/simple_gae_memoize
Author: Cesar Canassa
Author-email: cesar.canassa@gmail.com
License: BSD
Keywords: gae memcache memoize
Platform: UNKNOWN
Classifier: Development Status :: 2 - Pre-Alpha
Classifier: Topic :: Utilities
Classifier: License :: OSI Approved :: BSD License
